cyclone/__init__.py
cyclone/app.py
cyclone/appskel_default.zip
cyclone/appskel_foreman.zip
cyclone/appskel_signup.zip
cyclone/auth.py
cyclone/bottle.py
cyclone/escape.py
cyclone/httpclient.py
cyclone/httpserver.py
cyclone/httputil.py
cyclone/jsonrpc.py
cyclone/locale.py
cyclone/mail.py
cyclone/options.py
cyclone/redis.py
cyclone/sqlite.py
cyclone/sse.py
cyclone/template.py
cyclone/util.py
cyclone/web.py
cyclone/websocket.py
cyclone/xmlrpc.py
cyclone/testing/__init__.py
cyclone/testing/client.py
cyclone/testing/testcase.py
cyclone/tests/__init__.py
cyclone/tests/test_app.py
cyclone/tests/test_auth.py
cyclone/tests/test_db.py
cyclone/tests/test_escape.py
cyclone/tests/test_httpclient.py
cyclone/tests/test_httpserver.py
cyclone/tests/test_mail.py
cyclone/tests/test_template.py
cyclone/tests/test_testing.py
cyclone/tests/test_utils.py
cyclone/tests/test_web.py
cyclone-1.3.data/scripts/cyclone
twisted/plugins/cyclone_plugin.py
cyclone-1.3.dist-info/LICENSE
cyclone-1.3.dist-info/METADATA
cyclone-1.3.dist-info/WHEEL
cyclone-1.3.dist-info/top_level.txt
cyclone-1.3.dist-info/RECORD
