Metadata-Version: 2.1
Name: cyclone
Version: 1.3
Summary: Non-blocking web server for Python. Tornado API as a Twisted protocol.
Home-page: http://cyclone.io/
Author: fiorix
Author-email: fiorix@gmail.com
License: http://www.apache.org/licenses/LICENSE-2.0
Keywords: python non-blocking web server twisted facebook tornado
Platform: UNKNOWN
Classifier: Development Status :: 5 - Production/Stable
Classifier: Environment :: Web Environment
Classifier: Intended Audience :: Developers
Classifier: License :: OSI Approved :: Apache Software License
Classifier: Operating System :: POSIX
Classifier: Programming Language :: Python
Classifier: Programming Language :: Python :: 3
Classifier: Programming Language :: Python :: 3.5
Classifier: Programming Language :: Python :: 3.6
Classifier: Programming Language :: Python :: 3.7
Classifier: Programming Language :: Python :: 3 :: Only
Classifier: Topic :: Internet
Classifier: Topic :: Utilities
Classifier: Topic :: Software Development :: Libraries :: Python Modules
Classifier: Topic :: Internet :: WWW/HTTP
Classifier: Topic :: Internet :: WWW/HTTP :: WSGI
Classifier: Topic :: Internet :: WWW/HTTP :: WSGI :: Server
Classifier: Topic :: Internet :: WWW/HTTP :: Dynamic Content
Requires-Dist: twisted (==19.2.1)
Requires-Dist: pyOpenSSL (==19.0.0)
